krxmarket/__init__.py
krxmarket/performance.py
krxmarket/py.typed
krxmarket/stock_corps.py
krxmarket/version.py
krxmarket/common/__init__.py
krxmarket/common/exception.py
krxmarket/common/file.py
krxmarket/common/types.py
krxmarket/common/webrequest.py
krxmarket/common/xbrl/__init__.py
krxmarket/common/xbrl/helper.py
krxmarket/common/xbrl/util.py
krxmarket/common/xbrl/xbrl.py
krxmarket/common/xbrl/xbrl_table.py
krxmarket/dart/__init__.py
krxmarket/dart/api.py
krxmarket/dart/auth.py
krxmarket/dart/report_type.py
krxmarket/dart/request.py
krxmarket/dart/status.py
krxmarket/fnguide/__init__.py
krxmarket/fnguide/api.py
krxmarket/krx/__init__.py
krxmarket/krx/api.py
krxmarket-0.1.0.dist-info/LICENSE
krxmarket-0.1.0.dist-info/METADATA
krxmarket-0.1.0.dist-info/WHEEL
krxmarket-0.1.0.dist-info/top_level.txt
krxmarket-0.1.0.dist-info/RECORD
