Metadata-Version: 2.1
Name: krxmarket
Version: 0.1.0
Summary: read krxmarket information
Home-page: https://github.com/krosstrading/krxmarket
Author: Yongwoo Park
Author-email: nnnlife@gmail.com
License: MIT
Project-URL: Bug Reports, https://github.com/krosstrading/krxmarket/issues
Project-URL: Documentation, https://github.com/krosstrading/krxmarket
Keywords: krx,stock
Classifier: Development Status :: 5 - Production/Stable
Classifier: License :: OSI Approved :: MIT License
Classifier: Intended Audience :: Developers
Classifier: Topic :: Software Development :: Libraries :: Python Modules
Classifier: Operating System :: OS Independent
Classifier: Programming Language :: Python
Classifier: Programming Language :: Python :: 3
Classifier: Programming Language :: Python :: 3.7
Classifier: Programming Language :: Python :: 3.8
Classifier: Programming Language :: Python :: 3.9
Classifier: Programming Language :: Python :: 3.10
Classifier: Programming Language :: Python :: 3.11
Classifier: Programming Language :: Python :: Implementation :: PyPy
Classifier: Topic :: Software Development :: Libraries
License-File: LICENSE
Requires-Dist: requests
Requires-Dist: fake-useragent
Requires-Dist: xmltodict
Requires-Dist: bs4
Requires-Dist: pandas
Requires-Dist: arelle
Requires-Dist: lxml
Requires-Dist: isodate
Requires-Dist: openpyxl
Requires-Dist: python-dateutil
Provides-Extra: unicode_backport
